django_vite_app/__init__.py
django_vite_app/scripts/__init__.py
django_vite_app/scripts/create_project.py
django_vite_app-0.1.5.dist-info/METADATA
django_vite_app-0.1.5.dist-info/WHEEL
django_vite_app-0.1.5.dist-info/entry_points.txt
django_vite_app-0.1.5.dist-info/top_level.txt
django_vite_app-0.1.5.dist-info/RECORD
