Metadata-Version: 2.2
Name: django-vite-app
Version: 0.1.5
Summary: Script pour créer un projet Django avec Vite et Tailwind CSS
Author: Sidjane Assemien
Author-email: sidjaneassemien1@gmail.com
Classifier: Programming Language :: Python :: 3
Classifier: Framework :: Django
Classifier: Framework :: Django :: 4
Classifier: License :: OSI Approved :: MIT License
Classifier: Operating System :: OS Independent
Requires-Python: >=3.9
Requires-Dist: django>=4.0
Requires-Dist: djangorestframework
Requires-Dist: django-cors-headers
Dynamic: author
Dynamic: author-email
Dynamic: classifier
Dynamic: description
Dynamic: description-content-type
Dynamic: requires-dist
Dynamic: requires-python
Dynamic: summary
